cdk8s_image/__init__.py
cdk8s_image/py.typed
cdk8s_image/_jsii/__init__.py
cdk8s_image/_jsii/cdk8s-image@0.2.727.jsii.tgz
cdk8s_image-0.2.727.dist-info/LICENSE
cdk8s_image-0.2.727.dist-info/METADATA
cdk8s_image-0.2.727.dist-info/WHEEL
cdk8s_image-0.2.727.dist-info/top_level.txt
cdk8s_image-0.2.727.dist-info/RECORD
