Metadata-Version: 2.1
Name: cdk8s-image
Version: 0.2.727
Summary: Build & Push local docker images inside CDK8s applications
Home-page: https://github.com/cdk8s-team/cdk8s-image.git
Author: Amazon Web Services
License: Apache-2.0
Project-URL: Source, https://github.com/cdk8s-team/cdk8s-image.git
Classifier: Intended Audience :: Developers
Classifier: Operating System :: OS Independent
Classifier: Programming Language :: JavaScript
Classifier: Programming Language :: Python :: 3 :: Only
Classifier: Programming Language :: Python :: 3.9
Classifier: Programming Language :: Python :: 3.10
Classifier: Programming Language :: Python :: 3.11
Classifier: Typing :: Typed
Classifier: Development Status :: 5 - Production/Stable
Classifier: License :: OSI Approved
Requires-Python: ~=3.9
License-File: LICENSE
Requires-Dist: cdk8s <3.0.0,>=2.68.91
Requires-Dist: constructs <11.0.0,>=10.3.0
Requires-Dist: jsii <2.0.0,>=1.125.0
Requires-Dist: publication >=0.0.3
Requires-Dist: typeguard ==2.13.3
